LICENSE
MANIFEST.in
README.md
package.json
setup.py
dash_ace_persistent/DashAceEditor.py
dash_ace_persistent/__init__.py
dash_ace_persistent/_imports_.py
dash_ace_persistent/dash_ace_persistent.min.js
dash_ace_persistent/dash_ace_persistent.min.js.map
dash_ace_persistent/metadata.json
dash_ace_persistent/package-info.json
dash_ace_persistent.egg-info/PKG-INFO
dash_ace_persistent.egg-info/SOURCES.txt
dash_ace_persistent.egg-info/dependency_links.txt
dash_ace_persistent.egg-info/top_level.txt