Metadata-Version: 2.1
Name: dash-ace-persistent
Version: 0.3.4
Summary: Dash Ace Editor Component with persistence
Home-page: https://github.com/reasoned-ai/dash-ace
Author: james saunders <james@businessoptics.biz>
Author-email: xu@reasoned.ai
License: MIT
Platform: UNKNOWN
Classifier: Framework :: Dash
Requires-Python: >=3.6.0
